{
  "news": [
    {
      "title": "Naphtha Shortages Having a Growing Impact in Japan",
      "url": "https://www.nippon.com/en/japan-data/h02783/",
      "source": "Hacker News",
      "time": "2026-05-30T04:07:57.273388",
      "heat": 1000,
      "category": "tech"
    },
    {
      "title": "SQLite is all you need for durable workflows",
      "url": "https://obeli.sk/blog/sqlite-is-all-you-need-for-durable-workflows/",
      "source": "Hacker News",
      "time": "2026-05-30T04:07:57.419696",
      "heat": 950,
      "category": "tech"
    },
    {
      "title": "Snowboard Kids 2 is 100% Decompiled",
      "url": "https://blog.chrislewis.au/snowboard-kids-2-is-100-decompiled/",
      "source": "Hacker News",
      "time": "2026-05-30T04:07:57.707714",
      "heat": 850,
      "category": "tech"
    },
    {
      "title": "Perry Compiles TypeScript directly to executables using SWC and LLVM",
      "url": "https://www.perryts.com/",
      "source": "Hacker News",
      "time": "2026-05-30T04:07:57.857196",
      "heat": 800,
      "category": "tech"
    },
    {
      "title": "Notes from the Mistral AI Now Summit",
      "url": "https://koenvangilst.nl/lab/mistral-ai-now-summit",
      "source": "Hacker News",
      "time": "2026-05-30T04:07:58.005411",
      "heat": 750,
      "category": "tech"
    },
    {
      "title": "Print with dozens of colors: Our new open-source ColorMix for PrusaSlicer",
      "url": "https://blog.prusa3d.com/our-new-open-source-colormix-model-in-prusaslicer-and-easyprint_136079/",
      "source": "Hacker News",
      "time": "2026-05-30T04:07:58.151037",
      "heat": 700,
      "category": "tech"
    },
    {
      "title": "MCP is dead?",
      "url": "https://www.quandri.io/engineering-blog/mcp-is-dead",
      "source": "Hacker News",
      "time": "2026-05-30T04:07:58.302701",
      "heat": 650,
      "category": "tech"
    },
    {
      "title": "Math-to-Manim",
      "url": "https://github.com/HarleyCoops/Math-To-Manim",
      "source": "Hacker News",
      "time": "2026-05-30T04:07:58.455307",
      "heat": 600,
      "category": "tech"
    },
    {
      "title": "Shift will clean homes for free to train future robots",
      "url": "https://www.theverge.com/ai-artificial-intelligence/939765/ai-training-data-startup-shift-free-cleaning",
      "source": "Hacker News",
      "time": "2026-05-30T04:07:58.598342",
      "heat": 550,
      "category": "tech"
    },
    {
      "title": "junglivre/proxmox-backup-client-arm64",
      "url": "https://github.com/junglivre/proxmox-backup-client-arm64",
      "source": "GitHub",
      "time": "2026-05-30T04:07:59.605616",
      "heat": 5,
      "category": "tech"
    }
  ],
  "updated_at": "2026-05-30T04:07:59.606145"
}